setup.py
tkinter_stat/__init__.py
tkinter_stat.egg-info/PKG-INFO
tkinter_stat.egg-info/SOURCES.txt
tkinter_stat.egg-info/dependency_links.txt
tkinter_stat.egg-info/top_level.txt