Metadata-Version: 1.0
Name: tkinter-stat
Version: 1.0
Summary: 好用的tkinter状态栏/A useful tkinter statusbar plugin
Home-page: UNKNOWN
Author: Ruoyu Wang
Author-email: fuck@yopmail.com
License: UNKNOWN
Platform: UNKNOWN
